neurocurator/__init__.py
neurocurator/__main__.py
neurocurator/addOntoTermDlg.py
neurocurator/annotWidgets.py
neurocurator/annotationListModel.py
neurocurator/approximateMatchDlg.py
neurocurator/areaSelector.py
neurocurator/autocomplete.py
neurocurator/experimentalPropertyWgt.py
neurocurator/itemDelegates.py
neurocurator/jsonDlg.py
neurocurator/mainWin.py
neurocurator/modParamWidgets.py
neurocurator/paramFunctionWgt.py
neurocurator/paramRelationWgt.py
neurocurator/paramTraceWgt.py
neurocurator/paramValueWgt.py
neurocurator/proposer.py
neurocurator/qtOntoTrees.py
neurocurator/searchInterface.py
neurocurator/searchOntoWgt.py
neurocurator/settingsDlg.py
neurocurator/suggestedTagMng.py
neurocurator/tagWidget.py
neurocurator/uiUtilities.py
neurocurator/utils.py
neurocurator/variableTableWgt.py
neurocurator/zotero_edition.py
neurocurator/zotero_model.py
neurocurator/zotero_thread.py
neurocurator/zotero_widget.py
neurocurator-0.4.4.data/data/LICENSE.txt
neurocurator-0.4.4.dist-info/METADATA
neurocurator-0.4.4.dist-info/RECORD
neurocurator-0.4.4.dist-info/WHEEL
neurocurator-0.4.4.dist-info/entry_points.txt
neurocurator-0.4.4.dist-info/top_level.txt
