Metadata-Version: 2.1
Name: neurocurator
Version: 0.4.4
Summary: Application to perform curation of neuroscientific literature.
Home-page: https://github.com/BlueBrain/neurocurator
Author: Christian O'Reilly, Pierre-Alexandre Fonta
Author-email: christian.oreilly@epfl.ch, pierre-alexandre.fonta@epfl.ch
License: GPLv3
Keywords: neuroscience annotation curation literature modeling parameters
Platform: UNKNOWN
Classifier: Development Status :: 3 - Alpha
Classifier: Intended Audience :: Science/Research
Classifier: Topic :: Scientific/Engineering
Classifier: Environment :: X11 Applications :: Qt
Classifier: License :: OSI Approved :: GNU General Public License v3 (GPLv3)
Classifier: License :: Free for non-commercial use
Classifier: Programming Language :: Python :: 3 :: Only
Classifier: Programming Language :: Python :: 3.4
Classifier: Programming Language :: Python :: 3.5
Classifier: Programming Language :: Python :: 3.6
Classifier: Programming Language :: Python :: 3.7
Classifier: Operating System :: MacOS
Classifier: Operating System :: POSIX :: Linux
Classifier: Operating System :: Microsoft :: Windows
Classifier: Natural Language :: English
Requires-Python: >=3.4
Requires-Dist: nat (>=0.4.2)
Requires-Dist: PyQt5
Requires-Dist: numpy
Requires-Dist: pandas
Requires-Dist: wand
